tello/__init__.py
tello/demo.py
tello/frame2html.py
tello/stats.py
tello/tello.py
tello_python-1.1.6.dist-info/LICENSE
tello_python-1.1.6.dist-info/METADATA
tello_python-1.1.6.dist-info/WHEEL
tello_python-1.1.6.dist-info/top_level.txt
tello_python-1.1.6.dist-info/RECORD
