Metadata-Version: 2.1
Name: tello-python
Version: 1.1.6
Summary: Control DJI Tello drone with Python3
Home-page: https://github.com/cocpy/Tello-Python
Author: C灵C
Author-email: c0c@cocpy.com
License: UNKNOWN
Platform: UNKNOWN
Classifier: Programming Language :: Python :: 3
Classifier: License :: OSI Approved :: MIT License
Classifier: Operating System :: OS Independent
Requires-Dist: opencv-python
Requires-Dist: flask
Requires-Dist: paddlepaddle
Requires-Dist: paddlehub
